vtcff/__init__.py
vtcff/_args_subset.py
vtcff/_codec.py
vtcff/_codec_audio_copy.py
vtcff/_codec_audio_none.py
vtcff/_codec_avc.py
vtcff/_codec_avc_preset.py
vtcff/_codec_hevc.py
vtcff/_codec_prores_ks.py
vtcff/_codec_video_copy.py
vtcff/_colorspaces.py
vtcff/_command.py
vtcff/_common.py
vtcff/_filter_base.py
vtcff/_filter_crop.py
vtcff/_filter_pad.py
vtcff/_filter_swscale.py
vtcff/_filter_transpose.py
vtcff/_filter_zscale.py
vtcff/_math_cropping.py
vtcff/_math_padding.py
vtcff/_pf_10_pixfmts_stdout_parser.py
vtcff/_pf_15_pixfmt_subsampling.py
vtcff/_pf_20_pixfmt_bpc.py
vtcff/_time_span.py
vtcff-0.3.1.dist-info/LICENSE
vtcff-0.3.1.dist-info/METADATA
vtcff-0.3.1.dist-info/WHEEL
vtcff-0.3.1.dist-info/top_level.txt
vtcff-0.3.1.dist-info/RECORD
