Metadata-Version: 2.1
Name: vtcff
Version: 0.3.1
Summary: Ffmpeg wrapper for transcoding between video formats with an emphasis on maintaining quality and color depth in video production pipelines
Home-page: https://github.com/rtmigo/vtcff_py
Author: Artёm IG
Author-email: ortemeo@gmail.com
License: MIT
Keywords: ffmpeg,wrapper,codec,encoder,decoder,transcoding,video,audio
Platform: UNKNOWN
Classifier: Development Status :: 2 - Pre-Alpha
Classifier: License :: OSI Approved :: MIT License
Classifier: Programming Language :: Python :: 3.8
Classifier: Programming Language :: Python :: 3.9
Classifier: Programming Language :: Python :: 3.10
Classifier: Typing :: Typed
Classifier: Operating System :: POSIX
Classifier: Operating System :: Microsoft :: Windows
Requires-Python: >=3.8
License-File: LICENSE
Requires-Dist: framefile
